nonebot_plugin_saa_cx/__init__.py
nonebot_plugin_saa_cx/adapters/__init__.py
nonebot_plugin_saa_cx/adapters/discord.py
nonebot_plugin_saa_cx/adapters/feishu.py
nonebot_plugin_saa_cx/adapters/kaiheila.py
nonebot_plugin_saa_cx/adapters/onebot_v11.py
nonebot_plugin_saa_cx/adapters/onebot_v12.py
nonebot_plugin_saa_cx/adapters/qqguild.py
nonebot_plugin_saa_cx/adapters/red.py
nonebot_plugin_saa_cx/adapters/telegram.py
nonebot_plugin_saa_cx/types/__init__.py
nonebot_plugin_saa_cx/types/common_message_segment.py
nonebot_plugin_saa_cx/types/custom_message_segment.py
nonebot_plugin_saa_cx/utils/__init__.py
nonebot_plugin_saa_cx/utils/auto_select_bot.py
nonebot_plugin_saa_cx/utils/const.py
nonebot_plugin_saa_cx/utils/exceptions.py
nonebot_plugin_saa_cx/utils/helpers.py
nonebot_plugin_saa_cx/utils/platform_send_target.py
nonebot_plugin_saa_cx/utils/receipt.py
nonebot_plugin_saa_cx/utils/types.py
nonebot_plugin_spark_gpt/__init__.py
nonebot_plugin_spark_gpt/chatbots/__init__.py
nonebot_plugin_spark_gpt/chatbots/BaseChatBot.py
nonebot_plugin_spark_gpt/chatbots/BingBot.py
nonebot_plugin_spark_gpt/chatbots/ChatGPTApiBot.py
nonebot_plugin_spark_gpt/chatbots/ChatGPTWebBot.py
nonebot_plugin_spark_gpt/chatbots/ClaudeAiBot.py
nonebot_plugin_spark_gpt/chatbots/PoeBot.py
nonebot_plugin_spark_gpt/chatbots/SlackClaudeBot.py
nonebot_plugin_spark_gpt/const/__init__.py
nonebot_plugin_spark_gpt/const/menus.py
nonebot_plugin_spark_gpt/nonebot/__init__.py
nonebot_plugin_spark_gpt/nonebot/chat_consumer.py
nonebot_plugin_spark_gpt/nonebot/chat_manager.py
nonebot_plugin_spark_gpt/nonebot/command_manager.py
nonebot_plugin_spark_gpt/nonebot/model_manager.py
nonebot_plugin_spark_gpt/nonebot/prompt_manager.py
nonebot_plugin_spark_gpt/type_store/__init__.py
nonebot_plugin_spark_gpt/type_store/msgs_link.py
nonebot_plugin_spark_gpt/type_store/user_chat.py
nonebot_plugin_spark_gpt/type_store/web_config.py
nonebot_plugin_spark_gpt/utils/__init__.py
nonebot_plugin_spark_gpt/utils/decorators.py
nonebot_plugin_spark_gpt-2.0.3.dist-info/METADATA
nonebot_plugin_spark_gpt-2.0.3.dist-info/WHEEL
nonebot_plugin_spark_gpt-2.0.3.dist-info/RECORD
