Metadata-Version: 2.1
Name: nonebot_plugin_spark_gpt
Version: 2.0.3
Summary: Spark-GPT,将多种来源的gpt接入qq,TG,Kook,Discord及更多平台,提供webui进行实时配置热更新,效率高超,使用便捷,管理完善,功能强大
Author: canxin121
Author-email: 1969730106@qq.com
Requires-Python: >=3.8
Classifier: Programming Language :: Python :: 3
Classifier: Programming Language :: Python :: 3.8
Classifier: Programming Language :: Python :: 3.9
Classifier: Programming Language :: Python :: 3.10
Classifier: Programming Language :: Python :: 3.11
Requires-Dist: aiofiles (>=23.2.1)
Requires-Dist: aiohttp (>=3.8.5)
Requires-Dist: anyio (>=3.7.0)
Requires-Dist: async-bing-client (>=0.1.6)
Requires-Dist: async-claude-client (>=0.1.2)
Requires-Dist: async-poe-client (>=0.3.6)
Requires-Dist: httpx (>=0.24.1)
Requires-Dist: jinja2 (>=3.1.2)
Requires-Dist: markdown (>=3.4.4)
Requires-Dist: nonebot-plugin-alconna (>=0.27.2)
Requires-Dist: nonebot-plugin-bind (>=0.2.2)
Requires-Dist: nonebot-plugin-htmlrender (>=0.2.1)
Requires-Dist: nonebot-plugin-templates (>=0.1.6)
Requires-Dist: nonebot-plugin-web-config (>=0.1.3)
Requires-Dist: strenum (>=0.4.15)
Requires-Dist: tiktoken (>=0.4.0)
Requires-Dist: typing-extensions (>=4.7.1)
